{"nodes": [{"id": "pionex_bot_grid_strategy_py", "label": "grid_strategy.py", "file_type": "code", "source_file": "pionex-bot\\grid_strategy.py", "source_location": "L1"}, {"id": "grid_strategy_gridmode", "label": "GridMode", "file_type": "code", "source_file": "pionex-bot\\grid_strategy.py", "source_location": "L24"}, {"id": "enum", "label": "Enum", "file_type": "code", "source_file": "", "source_location": ""}, {"id": "grid_strategy_gridorderside", "label": "GridOrderSide", "file_type": "code", "source_file": "pionex-bot\\grid_strategy.py", "source_location": "L30"}, {"id": "grid_strategy_gridlevel", "label": "GridLevel", "file_type": "code", "source_file": "pionex-bot\\grid_strategy.py", "source_location": "L36"}, {"id": "grid_strategy_price_str", "label": "price_str()", "file_type": "code", "source_file": "pionex-bot\\grid_strategy.py", "source_location": "L46"}, {"id": "grid_strategy_gridstate", "label": "GridState", "file_type": "code", "source_file": "pionex-bot\\grid_strategy.py", "source_location": "L51"}, {"id": "grid_strategy_gridstate_to_dict", "label": ".to_dict()", "file_type": "code", "source_file": "pionex-bot\\grid_strategy.py", "source_location": "L59"}, {"id": "grid_strategy_from_dict", "label": "from_dict()", "file_type": "code", "source_file": "pionex-bot\\grid_strategy.py", "source_location": "L79"}, {"id": "grid_strategy_futuresgridstrategy", "label": "FuturesGridStrategy", "file_type": "code", "source_file": "pionex-bot\\grid_strategy.py", "source_location": "L97"}, {"id": "grid_strategy_futuresgridstrategy_init", "label": ".__init__()", "file_type": "code", "source_file": "pionex-bot\\grid_strategy.py", "source_location": "L112"}, {"id": "grid_strategy_futuresgridstrategy_create_grid_levels", "label": ".create_grid_levels()", "file_type": "code", "source_file": "pionex-bot\\grid_strategy.py", "source_location": "L160"}, {"id": "grid_strategy_futuresgridstrategy_get_orders_to_place", "label": ".get_orders_to_place()", "file_type": "code", "source_file": "pionex-bot\\grid_strategy.py", "source_location": "L191"}, {"id": "grid_strategy_futuresgridstrategy_mark_order_placed", "label": ".mark_order_placed()", "file_type": "code", "source_file": "pionex-bot\\grid_strategy.py", "source_location": "L211"}, {"id": "grid_strategy_futuresgridstrategy_process_fill", "label": ".process_fill()", "file_type": "code", "source_file": "pionex-bot\\grid_strategy.py", "source_location": "L222"}, {"id": "grid_strategy_futuresgridstrategy_check_stop_loss", "label": ".check_stop_loss()", "file_type": "code", "source_file": "pionex-bot\\grid_strategy.py", "source_location": "L282"}, {"id": "grid_strategy_futuresgridstrategy_check_out_of_range", "label": ".check_out_of_range()", "file_type": "code", "source_file": "pionex-bot\\grid_strategy.py", "source_location": "L298"}, {"id": "grid_strategy_futuresgridstrategy_get_stats", "label": ".get_stats()", "file_type": "code", "source_file": "pionex-bot\\grid_strategy.py", "source_location": "L308"}, {"id": "grid_strategy_futuresgridstrategy_save_state", "label": "._save_state()", "file_type": "code", "source_file": "pionex-bot\\grid_strategy.py", "source_location": "L336"}, {"id": "grid_strategy_futuresgridstrategy_load_state", "label": "._load_state()", "file_type": "code", "source_file": "pionex-bot\\grid_strategy.py", "source_location": "L344"}, {"id": "grid_strategy_futuresgridstrategy_reset_state", "label": ".reset_state()", "file_type": "code", "source_file": "pionex-bot\\grid_strategy.py", "source_location": "L355"}, {"id": "grid_strategy_rationale_1", "label": "Futures Grid Trading Strategy for Pionex.  Places a grid of limit orders acros", "file_type": "rationale", "source_file": "pionex-bot\\grid_strategy.py", "source_location": "L1"}, {"id": "grid_strategy_rationale_37", "label": "Represents one price level in the grid.", "file_type": "rationale", "source_file": "pionex-bot\\grid_strategy.py", "source_location": "L37"}, {"id": "grid_strategy_rationale_52", "label": "Persistent state of the grid bot.", "file_type": "rationale", "source_file": "pionex-bot\\grid_strategy.py", "source_location": "L52"}, {"id": "grid_strategy_rationale_98", "label": "Contract Grid Trading Strategy.      Parameters:         upper_price: Top of", "file_type": "rationale", "source_file": "pionex-bot\\grid_strategy.py", "source_location": "L98"}, {"id": "grid_strategy_rationale_161", "label": "Generate grid levels based on current price and mode.", "file_type": "rationale", "source_file": "pionex-bot\\grid_strategy.py", "source_location": "L161"}, {"id": "grid_strategy_rationale_192", "label": "Return grid levels that need orders placed.", "file_type": "rationale", "source_file": "pionex-bot\\grid_strategy.py", "source_location": "L192"}, {"id": "grid_strategy_rationale_212", "label": "Mark a grid level as having an active order.", "file_type": "rationale", "source_file": "pionex-bot\\grid_strategy.py", "source_location": "L212"}, {"id": "grid_strategy_rationale_223", "label": "Process a filled order. Returns the counter-order level to place.          Whe", "file_type": "rationale", "source_file": "pionex-bot\\grid_strategy.py", "source_location": "L223"}, {"id": "grid_strategy_rationale_283", "label": "Check if price has moved outside grid range by stop_loss_pct.", "file_type": "rationale", "source_file": "pionex-bot\\grid_strategy.py", "source_location": "L283"}, {"id": "grid_strategy_rationale_299", "label": "Check if current price is outside grid range.", "file_type": "rationale", "source_file": "pionex-bot\\grid_strategy.py", "source_location": "L299"}, {"id": "grid_strategy_rationale_356", "label": "Clear all grid state and start fresh.", "file_type": "rationale", "source_file": "pionex-bot\\grid_strategy.py", "source_location": "L356"}], "edges": [{"source": "pionex_bot_grid_strategy_py", "target": "json", "relation": "imports", "confidence": "EXTRACTED", "source_file": "pionex-bot\\grid_strategy.py", "source_location": "L11", "weight": 1.0}, {"source": "pionex_bot_grid_strategy_py", "target": "math", "relation": "imports", "confidence": "EXTRACTED", "source_file": "pionex-bot\\grid_strategy.py", "source_location": "L12", "weight": 1.0}, {"source": "pionex_bot_grid_strategy_py", "target": "os", "relation": "imports", "confidence": "EXTRACTED", "source_file": "pionex-bot\\grid_strategy.py", "source_location": "L13", "weight": 1.0}, {"source": "pionex_bot_grid_strategy_py", "target": "dataclasses", "relation": "imports_from", "confidence": "EXTRACTED", "source_file": "pionex-bot\\grid_strategy.py", "source_location": "L14", "weight": 1.0}, {"source": "pionex_bot_grid_strategy_py", "target": "enum", "relation": "imports_from", "confidence": "EXTRACTED", "source_file": "pionex-bot\\grid_strategy.py", "source_location": "L15", "weight": 1.0}, {"source": "pionex_bot_grid_strategy_py", "target": "typing", "relation": "imports_from", "confidence": "EXTRACTED", "source_file": "pionex-bot\\grid_strategy.py", "source_location": "L16", "weight": 1.0}, {"source": "pionex_bot_grid_strategy_py", "target": "logger", "relation": "imports_from", "confidence": "EXTRACTED", "source_file": "pionex-bot\\grid_strategy.py", "source_location": "L18", "weight": 1.0}, {"source": "pionex_bot_grid_strategy_py", "target": "utils", "relation": "imports_from", "confidence": "EXTRACTED", "source_file": "pionex-bot\\grid_strategy.py", "source_location": "L19", "weight": 1.0}, {"source": "pionex_bot_grid_strategy_py", "target": "grid_strategy_gridmode", "relation": "contains", "confidence": "EXTRACTED", "source_file": "pionex-bot\\grid_strategy.py", "source_location": "L24", "weight": 1.0}, {"source": "grid_strategy_gridmode", "target": "enum", "relation": "inherits", "confidence": "EXTRACTED", "source_file": "pionex-bot\\grid_strategy.py", "source_location": "L24", "weight": 1.0}, {"source": "pionex_bot_grid_strategy_py", "target": "grid_strategy_gridorderside", "relation": "contains", "confidence": "EXTRACTED", "source_file": "pionex-bot\\grid_strategy.py", "source_location": "L30", "weight": 1.0}, {"source": "grid_strategy_gridorderside", "target": "enum", "relation": "inherits", "confidence": "EXTRACTED", "source_file": "pionex-bot\\grid_strategy.py", "source_location": "L30", "weight": 1.0}, {"source": "pionex_bot_grid_strategy_py", "target": "grid_strategy_gridlevel", "relation": "contains", "confidence": "EXTRACTED", "source_file": "pionex-bot\\grid_strategy.py", "source_location": "L36", "weight": 1.0}, {"source": "pionex_bot_grid_strategy_py", "target": "grid_strategy_price_str", "relation": "contains", "confidence": "EXTRACTED", "source_file": "pionex-bot\\grid_strategy.py", "source_location": "L46", "weight": 1.0}, {"source": "pionex_bot_grid_strategy_py", "target": "grid_strategy_gridstate", "relation": "contains", "confidence": "EXTRACTED", "source_file": "pionex-bot\\grid_strategy.py", "source_location": "L51", "weight": 1.0}, {"source": "grid_strategy_gridstate", "target": "grid_strategy_gridstate_to_dict", "relation": "method", "confidence": "EXTRACTED", "source_file": "pionex-bot\\grid_strategy.py", "source_location": "L59", "weight": 1.0}, {"source": "pionex_bot_grid_strategy_py", "target": "grid_strategy_from_dict", "relation": "contains", "confidence": "EXTRACTED", "source_file": "pionex-bot\\grid_strategy.py", "source_location": "L79", "weight": 1.0}, {"source": "pionex_bot_grid_strategy_py", "target": "grid_strategy_futuresgridstrategy", "relation": "contains", "confidence": "EXTRACTED", "source_file": "pionex-bot\\grid_strategy.py", "source_location": "L97", "weight": 1.0}, {"source": "grid_strategy_futuresgridstrategy", "target": "grid_strategy_futuresgridstrategy_init", "relation": "method", "confidence": "EXTRACTED", "source_file": "pionex-bot\\grid_strategy.py", "source_location": "L112", "weight": 1.0}, {"source": "grid_strategy_futuresgridstrategy", "target": "grid_strategy_futuresgridstrategy_create_grid_levels", "relation": "method", "confidence": "EXTRACTED", "source_file": "pionex-bot\\grid_strategy.py", "source_location": "L160", "weight": 1.0}, {"source": "grid_strategy_futuresgridstrategy", "target": "grid_strategy_futuresgridstrategy_get_orders_to_place", "relation": "method", "confidence": "EXTRACTED", "source_file": "pionex-bot\\grid_strategy.py", "source_location": "L191", "weight": 1.0}, {"source": "grid_strategy_futuresgridstrategy", "target": "grid_strategy_futuresgridstrategy_mark_order_placed", "relation": "method", "confidence": "EXTRACTED", "source_file": "pionex-bot\\grid_strategy.py", "source_location": "L211", "weight": 1.0}, {"source": "grid_strategy_futuresgridstrategy", "target": "grid_strategy_futuresgridstrategy_process_fill", "relation": "method", "confidence": "EXTRACTED", "source_file": "pionex-bot\\grid_strategy.py", "source_location": "L222", "weight": 1.0}, {"source": "grid_strategy_futuresgridstrategy", "target": "grid_strategy_futuresgridstrategy_check_stop_loss", "relation": "method", "confidence": "EXTRACTED", "source_file": "pionex-bot\\grid_strategy.py", "source_location": "L282", "weight": 1.0}, {"source": "grid_strategy_futuresgridstrategy", "target": "grid_strategy_futuresgridstrategy_check_out_of_range", "relation": "method", "confidence": "EXTRACTED", "source_file": "pionex-bot\\grid_strategy.py", "source_location": "L298", "weight": 1.0}, {"source": "grid_strategy_futuresgridstrategy", "target": "grid_strategy_futuresgridstrategy_get_stats", "relation": "method", "confidence": "EXTRACTED", "source_file": "pionex-bot\\grid_strategy.py", "source_location": "L308", "weight": 1.0}, {"source": "grid_strategy_futuresgridstrategy", "target": "grid_strategy_futuresgridstrategy_save_state", "relation": "method", "confidence": "EXTRACTED", "source_file": "pionex-bot\\grid_strategy.py", "source_location": "L336", "weight": 1.0}, {"source": "grid_strategy_futuresgridstrategy", "target": "grid_strategy_futuresgridstrategy_load_state", "relation": "method", "confidence": "EXTRACTED", "source_file": "pionex-bot\\grid_strategy.py", "source_location": "L344", "weight": 1.0}, {"source": "grid_strategy_futuresgridstrategy", "target": "grid_strategy_futuresgridstrategy_reset_state", "relation": "method", "confidence": "EXTRACTED", "source_file": "pionex-bot\\grid_strategy.py", "source_location": "L355", "weight": 1.0}, {"source": "grid_strategy_from_dict", "target": "grid_strategy_gridlevel", "relation": "calls", "confidence": "EXTRACTED", "source_file": "pionex-bot\\grid_strategy.py", "source_location": "L86", "weight": 1.0}, {"source": "grid_strategy_from_dict", "target": "grid_strategy_gridorderside", "relation": "calls", "confidence": "EXTRACTED", "source_file": "pionex-bot\\grid_strategy.py", "source_location": "L89", "weight": 1.0}, {"source": "grid_strategy_futuresgridstrategy_init", "target": "grid_strategy_gridstate", "relation": "calls", "confidence": "EXTRACTED", "source_file": "pionex-bot\\grid_strategy.py", "source_location": "L146", "weight": 1.0}, {"source": "grid_strategy_futuresgridstrategy_init", "target": "grid_strategy_futuresgridstrategy_load_state", "relation": "calls", "confidence": "EXTRACTED", "source_file": "pionex-bot\\grid_strategy.py", "source_location": "L149", "weight": 1.0}, {"source": "grid_strategy_futuresgridstrategy_create_grid_levels", "target": "grid_strategy_gridlevel", "relation": "calls", "confidence": "EXTRACTED", "source_file": "pionex-bot\\grid_strategy.py", "source_location": "L176", "weight": 1.0}, {"source": "grid_strategy_futuresgridstrategy_create_grid_levels", "target": "grid_strategy_futuresgridstrategy_save_state", "relation": "calls", "confidence": "EXTRACTED", "source_file": "pionex-bot\\grid_strategy.py", "source_location": "L180", "weight": 1.0}, {"source": "grid_strategy_futuresgridstrategy_mark_order_placed", "target": "grid_strategy_futuresgridstrategy_save_state", "relation": "calls", "confidence": "EXTRACTED", "source_file": "pionex-bot\\grid_strategy.py", "source_location": "L220", "weight": 1.0}, {"source": "grid_strategy_futuresgridstrategy_process_fill", "target": "grid_strategy_futuresgridstrategy_save_state", "relation": "calls", "confidence": "EXTRACTED", "source_file": "pionex-bot\\grid_strategy.py", "source_location": "L272", "weight": 1.0}, {"source": "grid_strategy_futuresgridstrategy_save_state", "target": "grid_strategy_gridstate_to_dict", "relation": "calls", "confidence": "EXTRACTED", "source_file": "pionex-bot\\grid_strategy.py", "source_location": "L340", "weight": 1.0}, {"source": "grid_strategy_futuresgridstrategy_load_state", "target": "grid_strategy_from_dict", "relation": "calls", "confidence": "EXTRACTED", "source_file": "pionex-bot\\grid_strategy.py", "source_location": "L349", "weight": 1.0}, {"source": "grid_strategy_futuresgridstrategy_reset_state", "target": "grid_strategy_gridstate", "relation": "calls", "confidence": "EXTRACTED", "source_file": "pionex-bot\\grid_strategy.py", "source_location": "L357", "weight": 1.0}, {"source": "grid_strategy_rationale_1", "target": "pionex_bot_grid_strategy_py", "relation": "rationale_for", "confidence": "EXTRACTED", "source_file": "pionex-bot\\grid_strategy.py", "source_location": "L1", "weight": 1.0}, {"source": "grid_strategy_rationale_37", "target": "grid_strategy_gridlevel", "relation": "rationale_for", "confidence": "EXTRACTED", "source_file": "pionex-bot\\grid_strategy.py", "source_location": "L37", "weight": 1.0}, {"source": "grid_strategy_rationale_52", "target": "grid_strategy_gridstate", "relation": "rationale_for", "confidence": "EXTRACTED", "source_file": "pionex-bot\\grid_strategy.py", "source_location": "L52", "weight": 1.0}, {"source": "grid_strategy_rationale_98", "target": "grid_strategy_futuresgridstrategy", "relation": "rationale_for", "confidence": "EXTRACTED", "source_file": "pionex-bot\\grid_strategy.py", "source_location": "L98", "weight": 1.0}, {"source": "grid_strategy_rationale_161", "target": "grid_strategy_futuresgridstrategy_create_grid_levels", "relation": "rationale_for", "confidence": "EXTRACTED", "source_file": "pionex-bot\\grid_strategy.py", "source_location": "L161", "weight": 1.0}, {"source": "grid_strategy_rationale_192", "target": "grid_strategy_futuresgridstrategy_get_orders_to_place", "relation": "rationale_for", "confidence": "EXTRACTED", "source_file": "pionex-bot\\grid_strategy.py", "source_location": "L192", "weight": 1.0}, {"source": "grid_strategy_rationale_212", "target": "grid_strategy_futuresgridstrategy_mark_order_placed", "relation": "rationale_for", "confidence": "EXTRACTED", "source_file": "pionex-bot\\grid_strategy.py", "source_location": "L212", "weight": 1.0}, {"source": "grid_strategy_rationale_223", "target": "grid_strategy_futuresgridstrategy_process_fill", "relation": "rationale_for", "confidence": "EXTRACTED", "source_file": "pionex-bot\\grid_strategy.py", "source_location": "L223", "weight": 1.0}, {"source": "grid_strategy_rationale_283", "target": "grid_strategy_futuresgridstrategy_check_stop_loss", "relation": "rationale_for", "confidence": "EXTRACTED", "source_file": "pionex-bot\\grid_strategy.py", "source_location": "L283", "weight": 1.0}, {"source": "grid_strategy_rationale_299", "target": "grid_strategy_futuresgridstrategy_check_out_of_range", "relation": "rationale_for", "confidence": "EXTRACTED", "source_file": "pionex-bot\\grid_strategy.py", "source_location": "L299", "weight": 1.0}, {"source": "grid_strategy_rationale_356", "target": "grid_strategy_futuresgridstrategy_reset_state", "relation": "rationale_for", "confidence": "EXTRACTED", "source_file": "pionex-bot\\grid_strategy.py", "source_location": "L356", "weight": 1.0}]}